rideology2gpx-1.1.data/scripts/rideology2gpx
rideology2gpx_tool/__init__.py
rideology2gpx_tool/app_info.py
rideology2gpx_tool/cli.py
rideology2gpx_tool/data_file.py
rideology2gpx_tool/gpx_file.py
rideology2gpx_tool/main.py
rideology2gpx-1.1.dist-info/LICENSE
rideology2gpx-1.1.dist-info/METADATA
rideology2gpx-1.1.dist-info/WHEEL
rideology2gpx-1.1.dist-info/top_level.txt
rideology2gpx-1.1.dist-info/RECORD
