Metadata-Version: 2.1
Name: rideology2gpx
Version: 1.1
Summary: A simple command line program to transform log files obtained with the Kawasaki Rideology App into GPX files.
Author: Juan S. Bokser
Author-email: juan.bokser@gmail.com
Classifier: Programming Language :: Python :: 3
Requires-Python: >=3.6
License-File: LICENSE
Requires-Dist: beautifulsoup4 >=4.12.2
Requires-Dist: bs4 >=0.0.1
Requires-Dist: lxml >=4.9.2
Requires-Dist: click >=8.1.3
Requires-Dist: soupsieve >=2.4.1
Requires-Dist: tabulate >=0.9.0
Requires-Dist: plotly >=5.18.0
Requires-Dist: pandas >=2.0.3
Requires-Dist: kaleido >=0.2.1
